osc_tui/__init__.py
osc_tui/createImage.py
osc_tui/createKeyPair.py
osc_tui/createLoadbalancer.py
osc_tui/createNetAccessPoint.py
osc_tui/createSnapshot.py
osc_tui/createVm.py
osc_tui/createVolume.py
osc_tui/createVpcs.py
osc_tui/dhcpOptions.py
osc_tui/flexibleGPU.py
osc_tui/guiRules.py
osc_tui/imageGrid.py
osc_tui/inputForm.py
osc_tui/instancesGrid.py
osc_tui/internetServices.py
osc_tui/keyPairsGrid.py
osc_tui/loadbalancerGrid.py
osc_tui/main.py
osc_tui/mainForm.py
osc_tui/natServices.py
osc_tui/netAccesssPoint.py
osc_tui/netPeering.py
osc_tui/nicsGrid.py
osc_tui/popup.py
osc_tui/preloader.py
osc_tui/profileSelector.py
osc_tui/publicIps.py
osc_tui/routeTables.py
osc_tui/securityGroupsGrid.py
osc_tui/securityRulesGrid.py
osc_tui/selectableGrid.py
osc_tui/snapshotGrid.py
osc_tui/userGrid.py
osc_tui/virtualMachine.py
osc_tui/volumesGrid.py
osc_tui/vpcsGrid.py
osc_tui-25.3.0.dist-info/licenses/LICENSE
osc_tui-25.3.0.dist-info/METADATA
osc_tui-25.3.0.dist-info/WHEEL
osc_tui-25.3.0.dist-info/entry_points.txt
osc_tui-25.3.0.dist-info/top_level.txt
osc_tui-25.3.0.dist-info/RECORD
