Metadata-Version: 2.4
Name: osc-tui
Version: 25.3.0
Summary: Outscale
Home-page: http://www.outscale.com/
Author: Outscale SAS
Author-email: opensource@outscale.com
License-File: LICENSE
Requires-Dist: setuptools
Requires-Dist: requests>=2.28.1
Requires-Dist: osc-sdk-python>=0.26.0
Requires-Dist: pyperclip>=1.8.0
Requires-Dist: osc_diagram
Requires-Dist: osc_npyscreen
Requires-Dist: graphviz
Requires-Dist: requests
Dynamic: author
Dynamic: author-email
Dynamic: description
Dynamic: description-content-type
Dynamic: home-page
Dynamic: license-file
Dynamic: requires-dist
Dynamic: summary
